Workbook

Sheet VOC_Data
A1: Review_Id | B1: Source | C1: Source_Code | D1: Review_Date | E1: Rating | F1: Raw_Review_Text | G1: Issue | H1: Issue_Type | I1: Churn_Signal | J1: URL
A2: =IF(F2="","",C2&"_"&TEXT(COUNTIFS($C$2:C2,C2,$F$2:F2,"<>"),"000")) -> AS_AU_001 | B2: APP STORE AU | C2: AS_AU | D2: 45881 | E2: 2 | F2: I dont know why but when I try to add a task it wont let me add it and if I exit the app sometimes it adds but a majority of the time it isntI just got this thinking it would be good but its been 30 minutes of me trying to add my daily tasks when I can write them out in 5 | G2: {=_xlfn.XLOOKUP($A2,Tagged_Batch!$A:$A,Tagged_Batch!$B:$D,"")} -> Bug | H2: Tasks | I2: no | J2: null
A3: =IF(F3="","",C3&"_"&TEXT(COUNTIFS($C$2:C3,C3,$F$2:F3,"<>"),"000")) -> AS_AU_002 | B3: APP STORE AU | C3: AS_AU | D3: 45996 | E3: 2 | F3: Calendar entries are not always showing in Tiimo after recent app update. I have had to import the same calendars every day. Not retaining calendar imports makes weekly planning difficult. App on iPhone kept closing after opening when I also had the app open on my iPad. Very buggy. | G3: {=_xlfn.XLOOKUP($A3,Tagged_Batch!$A:$A,Tagged_Batch!$B:$D,"")} -> Bug | H3: Calendar | I3: no | J3: null
A4: =IF(F4="","",C4&"_"&TEXT(COUNTIFS($C$2:C4,C4,$F$2:F4,"<>"),"000")) -> AS_AU_003 | B4: APP STORE AU | C4: AS_AU | D4: 45993 | E4: 1 | F4: Extremely frustrating and not what you want when you have ADHD. You try to enter tasks or information and it just cuts you off. So it takes 15 minutes to enter a task or not at all. Ive tried re loading the app, updating my phone, turning my phone off and on - nothing. Not to mention you have to pay 60 in one go, so now youre just stuck with all these issues. I should have read past reviews. Its apparent this has been happening for 3 years with other customers. Maybe schedule a time to fix these issues Timmo | G4: {=_xlfn.XLOOKUP($A4,Tagged_Batch!$A:$A,Tagged_Batch!$B:$D,"")} -> Bug | H4: UI | I4: no | J4: null
A5: =IF(F5="","",C5&"_"&TEXT(COUNTIFS($C$2:C5,C5,$F$2:F5,"<>"),"000")) -> AS_AU_004 | B5: APP STORE AU | C5: AS_AU | D5: 45953 | E5: 1 | F5: I do NOT recommend. I got charged when I bought a free trial. And its the first time apple denied a refund and Tiimo has definitely denied it. Not worth the risk. developer writing to me- saying things that arent true- I never bought this app previously. | G5: {=_xlfn.XLOOKUP($A5,Tagged_Batch!$A:$A,Tagged_Batch!$B:$D,"")} -> Subscription | H5: Refund | I5: yes | J5: null
A6: =IF(F6="","",C6&"_"&TEXT(COUNTIFS($C$2:C6,C6,$F$2:F6,"<>"),"000")) -> AS_AU_005 | B6: APP STORE AU | C6: AS_AU | D6: 45946 | E6: 3 | F6: The calendar settings are a little clunky, so I find myself having to set events in my normal calendar and have it linked to Tiimo. App would be much better if the calendar settings were easier to use. | G6: {=_xlfn.XLOOKUP($A6,Tagged_Batch!$A:$A,Tagged_Batch!$B:$D,"")} -> UI | H6: Clutter | I6: no | J6: null
A7: =IF(F7="","",C7&"_"&TEXT(COUNTIFS($C$2:C7,C7,$F$2:F7,"<>"),"000")) -> AS_AU_006 | B7: APP STORE AU | C7: AS_AU | D7: 45881 | E7: 1 | F7: I cant sign into the app with my google account so I cant use it on my phone .major issue . | G7: {=_xlfn.XLOOKUP($A7,Tagged_Batch!$A:$A,Tagged_Batch!$B:$D,"")} -> Other | H7: Uncategorized | I7: no | J7: null
A8: =IF(F8="","",C8&"_"&TEXT(COUNTIFS($C$2:C8,C8,$F$2:F8,"<>"),"000")) -> AS_AU_007 | B8: APP STORE AU | C8: AS_AU | D8: 45845 | E8: 1 | F8: I signed up for the free trial and started adding in all my tasks, but after a few tasks had been added it kept taking me to the subscription page, even after Id already signed up for the free trial. So I signed up for a paid subscription which I knew I could still cancel, and it STILL kept taking me to the subscription page when I tried to add tasks. I have now cancelled my subscription and am disappointed this app wouldnt work for me. | G8: {=_xlfn.XLOOKUP($A8,Tagged_Batch!$A:$A,Tagged_Batch!$B:$D,"")} -> Subscription | H8: Paywall | I8: yes | J8: null
A9: =IF(F9="","",C9&"_"&TEXT(COUNTIFS($C$2:C9,C9,$F$2:F9,"<>"),"000")) -> AS_AU_008 | B9: APP STORE AU | C9: AS_AU | D9: 45803 | E9: 1 | F9: Im feeling so frustrated by tiiimo, it was meant to be a free app unless you wanted to pay, but I was charged for a whole year. And now when I see the app on my phone Im annoyed and dont even want to use it!! The time function is also really annoying, like no one has time or patience to scroll to find the time you want the thing to start on, just let us type it it just takes TOO long to set up the tasks. This needs to be way more efficient for adhd. We have like a 2 second window to get the info out honestly who is actually caring about if the task needs an emoji, its just a waste of time | G9: {=_xlfn.XLOOKUP($A9,Tagged_Batch!$A:$A,Tagged_Batch!$B:$D,"")} -> UI | H9: Setup | I9: yes | J9: null
A10: =IF(F10="","",C10&"_"&TEXT(COUNTIFS($C$2:C10,C10,$F$2:F10,"<>"),"000")) -> AS_AU_009 | B10: APP STORE AU | C10: AS_AU | D10: 46002 | E10: 2 | F10: This app is unusable without subscription | G10: {=_xlfn.XLOOKUP($A10,Tagged_Batch!$A:$A,Tagged_Batch!$B:$D,"")} -> Subscription | H10: Paywall | I10: no | J10: null
A11: =IF(F11="","",C11&"_"&TEXT(COUNTIFS($C$2:C11,C11,$F$2:F11,"<>"),"000")) -> AS_AU_010 | B11: APP STORE AU | C11: AS_AU | D11: 45996 | E11: 2 | F11: Calendar entries are not always showing in Tiimo after recent app update. I have had to import the same calendars every day. Not retaining calendar imports makes weekly planning difficult. App on iPhone kept closing after opening when I also had the app open on my iPad. Very buggy. | G11: {=_xlfn.XLOOKUP($A11,Tagged_Batch!$A:$A,Tagged_Batch!$B:$D,"")} -> Performance | H11: Crash | I11: no | J11: null
A12: =IF(F12="","",C12&"_"&TEXT(COUNTIFS($C$2:C12,C12,$F$2:F12,"<>"),"000")) -> AS_AU_011 | B12: APP STORE AU | C12: AS_AU | D12: 45947 | E12: 1 | F12: I was reviewing the app, with a plan for monthly subscription if I liked it. Decided I didnt theres a timer running constantly, which makes me anxious. And some bugs with task rollover. But they had already charged me for a 1 year subscription, not 1 month, no pro-rated cancellation, no way of reaching customer support. Thats pretty hostile for a supposed ADHD friendly app. | G12: {=_xlfn.XLOOKUP($A12,Tagged_Batch!$A:$A,Tagged_Batch!$B:$D,"")} -> Bug | H12: Tasks | I12: yes | J12: null
A13: =IF(F13="","",C13&"_"&TEXT(COUNTIFS($C$2:C13,C13,$F$2:F13,"<>"),"000")) -> AS_AU_012 | B13: APP STORE AU | C13: AS_AU | D13: 45803 | E13: 1 | F13: Im feeling so frustrated by tiiimo, it was meant to be a free app unless you wanted to pay, but I was charged for a whole year. And now when I see the app on my phone Im annoyed and dont even want to use it!! The time function is also really annoying, like no one has time or patience to scroll to find the time you want the thing to start on, just let us type it it just takes TOO long to set up the tasks. This needs to be way more efficient for adhd. We have like a 2 second window to get the info out honestly who is actually caring about if the task needs an emoji, its just a waste of time | G13: {=_xlfn.XLOOKUP($A13,Tagged_Batch!$A:$A,Tagged_Batch!$B:$D,"")} -> Subscription | H13: Paywall | I13: yes | J13: null
... A78: =IF(F78="","",C78&"_"&TEXT(COUNTIFS($C$2:C78,C78,$F$2:F78,"<>"),"000")) -> AS_US_036 | B78: APP STORE US | C78: AS_US | D78: 45910 | E78: 3 | F78: The desktop version doesn't synchronize with the iphone so you have to choose which platform you will use it on. The apple watch view doesn't include calendar information. I've put in requests for information and bug fixes with no response. I do like how the app functions on my phone. It is nice to have calendar appointments and a place for tasks to be listed and prioritized to structure my day. One of the bugs is needed to import the calendar every time the app is opened | G78: {=_xlfn.XLOOKUP($A78,Tagged_Batch!$A:$A,Tagged_Batch!$B:$D,"")} -> Bug | H78: Calendar | I78: no | J78: null
A79: =IF(F79="","",C79&"_"&TEXT(COUNTIFS($C$2:C79,C79,$F$2:F79,"<>"),"000")) -> BG_001 | B79: BLOG | C79: BG | D79: 46010 | E79: null | F79: Cons” section (learning curve; not ideal for minimalists). | G79: {=_xlfn.XLOOKUP($A79,Tagged_Batch!$A:$A,Tagged_Batch!$B:$D,"")} -> Other | H79: Uncategorized | I79: no | J79: https://twit.tv/posts/tech/how-tiimo-makes-task-and-time-management-easier-neurodiverse-users
A80: =IF(F80="","",C80&"_"&TEXT(COUNTIFS($C$2:C80,C80,$F$2:F80,"<>"),"000")) -> BG_002 | B80: BLOG | C80: BG | D80: 46035 | E80: null | F80: calls out “common criticism” such as learning curve and subscription price. | G80: {=_xlfn.XLOOKUP($A80,Tagged_Batch!$A:$A,Tagged_Batch!$B:$D,"")} -> Subscription | H80: High_Price | I80: no | J80: https://yourappland.com/tiimo-vs-structured-comparison/
A81: =IF(F81="","",C81&"_"&TEXT(COUNTIFS($C$2:C81,C81,$F$2:F81,"<>"),"000")) -> NT_001 | B81: NOLT | C81: NT | D81: 45658 | E81: null | F81: I really used the routine feature and I don’t mind that you guys changed it except for the fact that the sub tasks aren’t timed. I really used the timed sub tasks that automatically went on to the next one. That was one of the main reasons I used this app and bought premium was because the routines really helped me. Unfortunately this app is slightly less useful for me now and I don’t use it very often. Thank you for your consideration. | G81: {=_xlfn.XLOOKUP($A81,Tagged_Batch!$A:$A,Tagged_Batch!$B:$D,"")} -> Feature_Request | H81: Routines | I81: no | J81: https://tiimo.nolt.io/2794
A82: =IF(F82="","",C82&"_"&TEXT(COUNTIFS($C$2:C82,C82,$F$2:F82,"<>"),"000")) -> NT_002 | B82: NOLT | C82: NT | D82: 45658 | E82: null | F82: Really need auto save on this app. Sometimes I get distracted and move away from creating a task and it’ll just disappear and I have to start over. | G82: {=_xlfn.XLOOKUP($A82,Tagged_Batch!$A:$A,Tagged_Batch!$B:$D,"")} -> Feature_Request | H82: Uncategorized | I82: no | J82: https://tiimo.nolt.io/2555
A83: =IF(F83="","",C83&"_"&TEXT(COUNTIFS($C$2:C83,C83,$F$2:F83,"<>"),"000")) -> NT_003 | B83: NOLT | C83: NT | D83: 45658 | E83: null | F83: I NEED to time everything not just the main task to understand how long each sub task will take me, this can help calculate estimated time of main task vs actual time completed | G83: {=_xlfn.XLOOKUP($A83,Tagged_Batch!$A:$A,Tagged_Batch!$B:$D,"")} -> Other | H83: Uncategorized | I83: no | J83: https://tiimo.nolt.io/2553
A84: =IF(F84="","",C84&"_"&TEXT(COUNTIFS($C$2:C84,C84,$F$2:F84,"<>"),"000")) -> NT_004 | B84: NOLT | C84: NT | D84: 45658 | E84: null | F84: Please revert to the way routines were previously set up in the app. The removal of this feature makes the app far less useful to me. | G84: {=_xlfn.XLOOKUP($A84,Tagged_Batch!$A:$A,Tagged_Batch!$B:$D,"")} -> Feature_Request | H84: Routines | I84: no | J84: https://tiimo.nolt.io/2733
A85: =IF(F85="","",C85&"_"&TEXT(COUNTIFS($C$2:C85,C85,$F$2:F85,"<>"),"000")) -> NT_005 | B85: NOLT | C85: NT | D85: 46045 | E85: null | F85: Apple changed how widgets work, grr. Rather than being a live extension of the app they are now a snapshot of the app and any changes made need to be pushed to the widget. Please dear Tiimo developers can you integrate the new functionality (APNs) to push to widgets when changes have been made. | G85: {=_xlfn.XLOOKUP($A85,Tagged_Batch!$A:$A,Tagged_Batch!$B:$D,"")} -> Feature_Request | H85: Widgets | I85: no | J85: https://tiimo.nolt.io/3980
A86: =IF(F86="","",C86&"_"&TEXT(COUNTIFS($C$2:C86,C86,$F$2:F86,"<>"),"000")) -> NT_006 | B86: NOLT | C86: NT | D86: 46043 | E86: null | F86: Create features for people always traveling / digital nomads | G86: {=_xlfn.XLOOKUP($A86,Tagged_Batch!$A:$A,Tagged_Batch!$B:$D,"")} -> Feature_Request | H86: Uncategorized | I86: no | J86: https://tiimo.nolt.io/3969
A87: =IF(F87="","",C87&"_"&TEXT(COUNTIFS($C$2:C87,C87,$F$2:F87,"<>"),"000")) -> NT_007 | B87: NOLT | C87: NT | D87: 46041 | E87: null | F87: It would be very helpful to have a way to retain routines and insert as needed. For example, clean a bedroom. The suggested tasks were not the same as what I need so I created my own list. It would be nice to have a specific space to keep the routine to move it to the day I have available to clean the room. I have it in to do but it’s just too cluttered there. | G87: {=_xlfn.XLOOKUP($A87,Tagged_Batch!$A:$A,Tagged_Batch!$B:$D,"")} -> Feature_Request | H87: Routines | I87: no | J87: https://tiimo.nolt.io/3963
A88: =IF(F88="","",C88&"_"&TEXT(COUNTIFS($C$2:C88,C88,$F$2:F88,"<>"),"000")) -> NT_008 | B88: NOLT | C88: NT | D88: 46041 | E88: null | F88: the ai is very difficult to use. it doesn’t do what i ask it when i list tasks, and it straight up stopped responding to me after sending it tasks. unfortunately, this feature seems incomplete. it works hit or miss for me, at best :( | G88: {=_xlfn.XLOOKUP($A88,Tagged_Batch!$A:$A,Tagged_Batch!$B:$D,"")} -> Bug | H88: AI | I88: no | J88: https://tiimo.nolt.io/3979
A89: =IF(F89="","",C89&"_"&TEXT(COUNTIFS($C$2:C89,C89,$F$2:F89,"<>"),"000")) -> NT_009 | B89: NOLT | C89: NT | D89: 46037 | E89: null | F89: Don't force peolpe to sign up to a free tiral just to try it | G89: {=_xlfn.XLOOKUP($A89,Tagged_Batch!$A:$A,Tagged_Batch!$B:$D,"")} -> Subscription | H89: Paywall | I89: no | J89: https://tiimo.nolt.io/3949
A90: =IF(F90="","",C90&"_"&TEXT(COUNTIFS($C$2:C90,C90,$F$2:F90,"<>"),"000")) -> NT_010 | B90: NOLT | C90: NT | D90: 46037 | E90: null | F90: I’m happy to pay what I need to but just want to know that what I’m paying for will work for me. Trying to assess that in a week is like asking me to completely assemble a rocket ship (without an instruction manual) in one week | G90: {=_xlfn.XLOOKUP($A90,Tagged_Batch!$A:$A,Tagged_Batch!$B:$D,"")} -> Subscription | H90: Uncategorized | I90: no | J90: https://tiimo.nolt.io/3948
... A113: =IF(F113="","",C113&"_"&TEXT(COUNTIFS($C$2:C113,C113,$F$2:F113,"<>"),"000")) -> RD_014 | B113: REDDIT | C113: RD | D113: 45717 | E113: null | F113: I’ve been using Tiimo for almost a year now, and I love it because I’m terrible at keeping track of time. They took routines away a while back, and I think it was a bad move, but I continued to use the app. Fast-forward to now, and I’m disappointed because the app is more buggy than ever. | G113: {=_xlfn.XLOOKUP($A113,Tagged_Batch!$A:$A,Tagged_Batch!$B:$D,"")} -> Bug | H113: Uncategorized | I113: no | J113: https://www.reddit.com/r/ADHD/comments/1jff09x/recommendations_for_apps_similar_to_tiimo/
A114: =IF(F114="","",C114&"_"&TEXT(COUNTIFS($C$2:C114,C114,$F$2:F114,"<>"),"000")) -> TP_001 | B114: TRUST PILOT | C114: TP | D114: 46042 | E114: 1 | F114: The took money and i have no access. Wrote many emails - zero contact. Cannot even cancel subsricption as I have no access to the account. this is beyond ridiculous. I dont believe they have any customer service team at all. NO ONE IS RESPONDING - not even an automatic email. But payment was taken - they didnt have problem with that. Another SCAM???? | G114: {=_xlfn.XLOOKUP($A114,Tagged_Batch!$A:$A,Tagged_Batch!$B:$D,"")} -> Subscription | H114: Refund | I114: yes | J114: https://www.trustpilot.com/review/tiimoapp.com?stars=1

Sheet Tagged_Batch
A1: Review_Id | B1: Issue | C1: Issue_Type | D1: Churn_Signal
A2: AS_AU_001 | B2: Bug | C2: Tasks | D2: no
A3: AS_AU_002 | B3: Bug | C3: Calendar | D3: no
A4: AS_AU_003 | B4: Bug | C4: UI | D4: no
A5: AS_AU_004 | B5: Subscription | C5: Refund | D5: yes
A6: AS_AU_005 | B6: UI | C6: Clutter | D6: no
A7: AS_AU_006 | B7: Other | C7: Uncategorized | D7: no
A8: AS_AU_007 | B8: Subscription | C8: Paywall | D8: yes
A9: AS_AU_008 | B9: UI | C9: Setup | D9: yes
A10: AS_AU_009 | B10: Subscription | C10: Paywall | D10: no
A11: AS_AU_010 | B11: Performance | C11: Crash | D11: no
A12: AS_AU_011 | B12: Bug | C12: Tasks | D12: yes
... A114: TP_001 | B114: Subscription | C114: Refund | D114: yes

Sheet Pivot Table
B1: Column Labels
B2: no | E2: yes | H2: Total Count of Issue | I2: Total Percent of Issue | J2: Total Percent of Churn issues
A3: Row Labels | B3: Count of Issue | C3: Percent of Issue | D3: Percent of Churn issues | E3: Count of Issue | F3: Percent of Issue | G3: Percent of Churn issues
A4: Bug | B4: 15 | C4: 0.13274336 | D4: 0.19736842 | E4: 11 | F4: 0.097345133 | G4: 0.2972973 | H4: 26 | I4: 0.2300885 | J4: 0.2300885
A5: AI | B5: 1 | C5: 0.0088495575 | D5: 0.013157895 | F5: 0 | G5: 0 | H5: 1 | I5: 0.0088495575 | J5: 0.0088495575
A6: Calendar | B6: 7 | C6: 0.061946903 | D6: 0.092105263 | E6: 2 | F6: 0.017699115 | G6: 0.054054054 | H6: 9 | I6: 0.079646018 | J6: 0.079646018
A7: Notifications | C7: 0 | D7: 0 | E7: 1 | F7: 0.0088495575 | G7: 0.027027027 | H7: 1 | I7: 0.0088495575 | J7: 0.0088495575
A8: Routines | B8: 1 | C8: 0.0088495575 | D8: 0.013157895 | F8: 0 | G8: 0 | H8: 1 | I8: 0.0088495575 | J8: 0.0088495575
A9: Tasks | B9: 1 | C9: 0.0088495575 | D9: 0.013157895 | E9: 1 | F9: 0.0088495575 | G9: 0.027027027 | H9: 2 | I9: 0.017699115 | J9: 0.017699115
A10: Timers | C10: 0 | D10: 0 | E10: 1 | F10: 0.0088495575 | G10: 0.027027027 | H10: 1 | I10: 0.0088495575 | J10: 0.0088495575
A11: UI | B11: 4 | C11: 0.03539823 | D11: 0.052631579 | E11: 3 | F11: 0.026548673 | G11: 0.081081081 | H11: 7 | I11: 0.061946903 | J11: 0.061946903
A12: Uncategorized | B12: 1 | C12: 0.0088495575 | D12: 0.013157895 | E12: 3 | F12: 0.026548673 | G12: 0.081081081 | H12: 4 | I12: 0.03539823 | J12: 0.03539823
A13: Feature_Request | B13: 26 | C13: 0.2300885 | D13: 0.34210526 | E13: 5 | F13: 0.044247788 | G13: 0.13513514 | H13: 31 | I13: 0.27433628 | J13: 0.27433628
A14: Alerts | B14: 1 | C14: 0.0088495575 | D14: 0.013157895 | F14: 0 | G14: 0 | H14: 1 | I14: 0.0088495575 | J14: 0.0088495575
A15: Routines | B15: 20 | C15: 0.17699115 | D15: 0.26315789 | E15: 5 | F15: 0.044247788 | G15: 0.13513514 | H15: 25 | I15: 0.22123894 | J15: 0.22123894
A16: Uncategorized | B16: 4 | C16: 0.03539823 | D16: 0.052631579 | F16: 0 | G16: 0 | H16: 4 | I16: 0.03539823 | J16: 0.03539823
A17: Widgets | B17: 1 | C17: 0.0088495575 | D17: 0.013157895 | F17: 0 | G17: 0 | H17: 1 | I17: 0.0088495575 | J17: 0.0088495575
A18: Integrations | B18: 10 | C18: 0.088495575 | D18: 0.13157895 | E18: 4 | F18: 0.03539823 | G18: 0.10810811 | H18: 14 | I18: 0.12389381 | J18: 0.12389381
A19: Android | B19: 4 | C19: 0.03539823 | D19: 0.052631579 | F19: 0 | G19: 0 | H19: 4 | I19: 0.03539823 | J19: 0.03539823
A20: Apple_Watch | B20: 4 | C20: 0.03539823 | D20: 0.052631579 | E20: 1 | F20: 0.0088495575 | G20: 0.027027027 | H20: 5 | I20: 0.044247788 | J20: 0.044247788
A21: Calendar | B21: 1 | C21: 0.0088495575 | D21: 0.013157895 | E21: 1 | F21: 0.0088495575 | G21: 0.027027027 | H21: 2 | I21: 0.017699115 | J21: 0.017699115
A22: Google_Calendar | B22: 1 | C22: 0.0088495575 | D22: 0.013157895 | E22: 1 | F22: 0.0088495575 | G22: 0.027027027 | H22: 2 | I22: 0.017699115 | J22: 0.017699115
A23: Web_Desktop | C23: 0 | D23: 0 | E23: 1 | F23: 0.0088495575 | G23: 0.027027027 | H23: 1 | I23: 0.0088495575 | J23: 0.0088495575
A24: Other | B24: 7 | C24: 0.061946903 | D24: 0.092105263 | E24: 1 | F24: 0.0088495575 | G24: 0.027027027 | H24: 8 | I24: 0.07079646 | J24: 0.07079646
A25: Uncategorized | B25: 7 | C25: 0.061946903 | D25: 0.092105263 | E25: 1 | F25: 0.0088495575 | G25: 0.027027027 | H25: 8 | I25: 0.07079646 | J25: 0.07079646
A26: Performance | B26: 2 | C26: 0.017699115 | D26: 0.026315789 | E26: 3 | F26: 0.026548673 | G26: 0.081081081 | H26: 5 | I26: 0.044247788 | J26: 0.044247788
A27: Crash | B27: 2 | C27: 0.017699115 | D27: 0.026315789 | E27: 3 | F27: 0.026548673 | G27: 0.081081081 | H27: 5 | I27: 0.044247788 | J27: 0.044247788
A28: Subscription | B28: 10 | C28: 0.088495575 | D28: 0.13157895 | E28: 9 | F28: 0.079646018 | G28: 0.24324324 | H28: 19 | I28: 0.16814159 | J28: 0.16814159
A29: Auto_Renew_Charge | B29: 1 | C29: 0.0088495575 | D29: 0.013157895 | F29: 0 | G29: 0 | H29: 1 | I29: 0.0088495575 | J29: 0.0088495575
A30: High_Price | B30: 1 | C30: 0.0088495575 | D30: 0.013157895 | E30: 1 | F30: 0.0088495575 | G30: 0.027027027 | H30: 2 | I30: 0.017699115 | J30: 0.017699115
A31: Paywall | B31: 4 | C31: 0.03539823 | D31: 0.052631579 | E31: 4 | F31: 0.03539823 | G31: 0.10810811 | H31: 8 | I31: 0.07079646 | J31: 0.07079646
A32: Refund | C32: 0 | D32: 0 | E32: 4 | F32: 0.03539823 | G32: 0.10810811 | H32: 4 | I32: 0.03539823 | J32: 0.03539823
A33: Uncategorized | B33: 4 | C33: 0.03539823 | D33: 0.052631579 | F33: 0 | G33: 0 | H33: 4 | I33: 0.03539823 | J33: 0.03539823
A34: UI | B34: 6 | C34: 0.053097345 | D34: 0.078947368 | E34: 4 | F34: 0.03539823 | G34: 0.10810811 | H34: 10 | I34: 0.088495575 | J34: 0.088495575
A35: Clutter | B35: 3 | C35: 0.026548673 | D35: 0.039473684 | E35: 1 | F35: 0.0088495575 | G35: 0.027027027 | H35: 4 | I35: 0.03539823 | J35: 0.03539823
A36: Setup | B36: 1 | C36: 0.0088495575 | D36: 0.013157895 | E36: 1 | F36: 0.0088495575 | G36: 0.027027027 | H36: 2 | I36: 0.017699115 | J36: 0.017699115
A37: Uncategorized | B37: 2 | C37: 0.017699115 | D37: 0.026315789 | E37: 2 | F37: 0.017699115 | G37: 0.054054054 | H37: 4 | I37: 0.03539823 | J37: 0.03539823
A38: Grand Total | B38: 76 | C38: 0.67256637 | D38: 1 | E38: 37 | F38: 0.32743363 | G38: 1 | H38: 113 | I38: 1 | J38: 1

Sheet Stakeholder Matrix
A1: Stakeholder Name | B1: Role/Category | C1: Power | D1: Interest | E1: Composite Score | F1: Power-Interest Quadrant | G1: Engagement Strategy | H1: Elicitation Techniques | I1: Elicitation Priority
A2: Neurodivergent Users | B2: Core Customers | C2: 3 | D2: 9 | E2: =TB_Stakholder_Matrix[[#This Row],[Power ]]*TB_Stakholder_Matrix[[#This Row],[Interest ]] -> 27 | F2: Keep Informed | G2: Newsletters | H2: Document Analysis (reviews) | I2: Phase 3
A3: Regular Users | B3: Customers | C3: 2 | D3: 9 | E3: =TB_Stakholder_Matrix[[#This Row],[Power ]]*TB_Stakholder_Matrix[[#This Row],[Interest ]] -> 18 | F3: Keep Informed | G3: Newsletters | H3: Document Analysis (reviews) | I3: Phase 3
A4: Product Managers | B4: Internal Strategy | C4: 9 | D4: 10 | E4: =TB_Stakholder_Matrix[[#This Row],[Power ]]*TB_Stakholder_Matrix[[#This Row],[Interest ]] -> 90 | F4: Manage Closely | G4: Weekly 1:1s, Joint prioritization workshops | H4: Interviews & Workshops | I4: Phase 1
A5: Executive Management | B5: Internal Strategy | C5: 10 | D5: 10 | E5: =TB_Stakholder_Matrix[[#This Row],[Power ]]*TB_Stakholder_Matrix[[#This Row],[Interest ]] -> 100 | F5: Manage Closely | G5: Monthly executive briefings, ROI validation reviews | H5: Presentation & Decision Reviews | I5: Phase 1
A6: Development Lead | B6: Internal Strategy | C6: 8 | D6: 10 | E6: =TB_Stakholder_Matrix[[#This Row],[Power ]]*TB_Stakholder_Matrix[[#This Row],[Interest ]] -> 80 | F6: Manage Closely | G6: Weekly 1:1s, Technical feasibility workshops | H6: Collaborative technical roadmap sessions | I6: Phase 1
A7: Design Lead | B7: Internal Strategy | C7: 8 | D7: 10 | E7: =TB_Stakholder_Matrix[[#This Row],[Power ]]*TB_Stakholder_Matrix[[#This Row],[Interest ]] -> 80 | F7: Manage Closely | G7: Weekly 1:1s, design discussion workshops | H7: Collaborative design roadmap sessions | I7: Phase 1
A8: Support Team | B8: Internal Service | C8: 4 | D8: 6 | E8: =TB_Stakholder_Matrix[[#This Row],[Power ]]*TB_Stakholder_Matrix[[#This Row],[Interest ]] -> 24 | F8: Keep Informed | G8: Bi-weekly complaint trend updates, Requirements feedback | H8: Surveys & Data Sharing | I8: Phase 3
A9: Development Team | B9: Internal Delivery | C9: 7.5 | D9: 9 | E9: =TB_Stakholder_Matrix[[#This Row],[Power ]]*TB_Stakholder_Matrix[[#This Row],[Interest ]] -> 67.5 | F9: Manage Closely | G9: Technical Feasibility Workshops, Sprint planning, Backlog refinement meetings | H9: Collaborative development sessions | I9: Phase 2
A10: QA/ Testing Team | B10: Internal Delivery | C10: 7 | D10: 9 | E10: =TB_Stakholder_Matrix[[#This Row],[Power ]]*TB_Stakholder_Matrix[[#This Row],[Interest ]] -> 63 | F10: Manage Closely | G10: Technical Feasibility Workshops, Sprint Planning | H10: Collaborative sessions to design test plans | I10: Phase 2
A11: Data Analytics Team | B11: Internal Service | C11: 5 | D11: 6 | E11: =TB_Stakholder_Matrix[[#This Row],[Power ]]*TB_Stakholder_Matrix[[#This Row],[Interest ]] -> 30 | F11: Keep Informed | G11: Monthly churn dashboard reviews, Metrics validation | H11: Data workshops and reports | I11: Phase 3
A12: Design Team | B12: Internal Delivery | C12: 8 | D12: 9 | E12: =TB_Stakholder_Matrix[[#This Row],[Power ]]*TB_Stakholder_Matrix[[#This Row],[Interest ]] -> 72 | F12: Manage Closely | G12: Weekly UX reviews, Routines wireframe walkthroughs | H12: Collaborative design sessions | I12: Phase 2
A13: Apple App Store Team | B13: External Regulator | C13: 8 | D13: 2 | E13: =TB_Stakholder_Matrix[[#This Row],[Power ]]*TB_Stakholder_Matrix[[#This Row],[Interest ]] -> 16 | F13: Keep Satisfied | G13: Compliance monitoring | H13: Market Analysis | I13: Phase 3
... A16: Influencers | B16: External Community | C16: 2 | D16: 7 | E16: =TB_Stakholder_Matrix[[#This Row],[Power ]]*TB_Stakholder_Matrix[[#This Row],[Interest ]] -> 14 | F16: Keep Informed | G16: Quarterly Content Reviews, Social Listening | H16: Social Analysis | I16: Phase 3
A19: Chart Axis | B19: 5 | C19: 5

Sheet Power Interest Grid
